hippo2client/__init__.py
hippo2client/hippo2client.py
hippo2client-1.6.dist-info/METADATA
hippo2client-1.6.dist-info/WHEEL
hippo2client-1.6.dist-info/top_level.txt
hippo2client-1.6.dist-info/RECORD
