Metadata-Version: 2.1
Name: hippo2client
Version: 1.6
Summary: Client Adapter to Hippo2D
Home-page: http://github.com/hgn/hippo2client
Author: Hagen Paul Pfeifer
Author-email: hagen@jauu.net
License: MIT
Platform: UNKNOWN
Classifier: Development Status :: 4 - Beta
Classifier: Intended Audience :: Developers
Classifier: Topic :: Software Development :: Build Tools
Classifier: License :: OSI Approved :: MIT License
Classifier: Programming Language :: Python :: 2
Classifier: Programming Language :: Python :: 2.6
Classifier: Programming Language :: Python :: 2.7
Classifier: Programming Language :: Python :: 3
Classifier: Programming Language :: Python :: 3.6
Classifier: Programming Language :: Python :: 3.7
